{
  "TopCombinations": [
    {
      "HostViewModel": null,
      "AltModelKey": null,
      "IsInPopupContext": false,
      "UnitTypes": "All",
      "UnitLocations": "All",
      "Id": "top_combination_1",
      "ObjectId": 0,
      "ValveId": null,
      "Weighting": 10,
      "BibItem": null,
      "PathToBackgroundImage": null,
      "TextColor": null,
      "TextSelectedColor": null,
      "ButtonType": "TopCombination",
      "ButtonModelList": [],
      "behaviors": "Tap",
      "RecipeId": "",
      "ResourceId": null,
      "IsPlaceHolder": false,
      "HasImage": false,
      "IsSelected": false,
      "Label": "",
      "IsDisabled": false,
      "AllowSelectionOnDisabled": false,
      "FooterIcon": "None",
      "FooterColor": "Gray",
      "ItemStatus": "None",
      "FooterText": null,
      "FooterFontColor": "White",
      "PathToImage": "",
      "BackgroundColor": "#FFC8C8C8",
      "RowNumber": 0,
      "Tag": null,
      "ActionId": ""
    },
    {
      "HostViewModel": null,
      "AltModelKey": null,
      "IsInPopupContext": false,
      "UnitTypes": "All",
      "UnitLocations": "All",
      "Id": "top_combination_2",
      "ObjectId": 0,
      "ValveId": null,
      "Weighting": 10,
      "BibItem": null,
      "PathToBackgroundImage": null,
      "TextColor": null,
      "TextSelectedColor": null,
      "ButtonType": "TopCombination",
      "ButtonModelList": [],
      "behaviors": "Tap",
      "RecipeId": "",
      "ResourceId": null,
      "IsPlaceHolder": false,
      "HasImage": false,
      "IsSelected": false,
      "Label": "",
      "IsDisabled": false,
      "AllowSelectionOnDisabled": false,
      "FooterIcon": "None",
      "FooterColor": "Gray",
      "ItemStatus": "None",
      "FooterText": null,
      "FooterFontColor": "White",
      "PathToImage": "",
      "BackgroundColor": "#FFC8C8C8",
      "RowNumber": 0,
      "Tag": null,
      "ActionId": ""
    },
    {
      "HostViewModel": null,
      "AltModelKey": null,
      "IsInPopupContext": false,
      "UnitTypes": "All",
      "UnitLocations": "All",
      "Id": "top_combination_3",
      "ObjectId": 0,
      "ValveId": null,
      "Weighting": 10,
      "BibItem": null,
      "PathToBackgroundImage": null,
      "TextColor": null,
      "TextSelectedColor": null,
      "ButtonType": "TopCombination",
      "ButtonModelList": [],
      "behaviors": "Tap",
      "RecipeId": "",
      "ResourceId": null,
      "IsPlaceHolder": false,
      "HasImage": false,
      "IsSelected": false,
      "Label": "",
      "IsDisabled": false,
      "AllowSelectionOnDisabled": false,
      "FooterIcon": "None",
      "FooterColor": "Gray",
      "ItemStatus": "None",
      "FooterText": null,
      "FooterFontColor": "White",
      "PathToImage": "",
      "BackgroundColor": "#FFC8C8C8",
      "RowNumber": 0,
      "Tag": null,
      "ActionId": ""
    },
    {
      "HostViewModel": null,
      "AltModelKey": null,
      "IsInPopupContext": false,
      "UnitTypes": "All",
      "UnitLocations": "All",
      "Id": "top_combination_4",
      "ObjectId": 0,
      "ValveId": null,
      "Weighting": 10,
      "BibItem": null,
      "PathToBackgroundImage": null,
      "TextColor": null,
      "TextSelectedColor": null,
      "ButtonType": "TopCombination",
      "ButtonModelList": [],
      "behaviors": "Tap",
      "RecipeId": "",
      "ResourceId": null,
      "IsPlaceHolder": false,
      "HasImage": false,
      "IsSelected": false,
      "Label": "",
      "IsDisabled": false,
      "AllowSelectionOnDisabled": false,
      "FooterIcon": "None",
      "FooterColor": "Gray",
      "ItemStatus": "None",
      "FooterText": null,
      "FooterFontColor": "White",
      "PathToImage": "",
      "BackgroundColor": "#FFC8C8C8",
      "RowNumber": 0,
      "Tag": null,
      "ActionId": ""
    }
  ]
}