{
  "Version": "1.0",
  "CountryLanguageCode": "en-us",
  "Label": "English (United States)",
  "ResourceStrings": {
    "waiting_for_cup": "Waiting for cup...",
    "topping_off": "Topping Off...",
    "country_code_en_us_id": "en-US",
    "country_code_fr_ca_id": "fr-CA",
    "country_code_es_mx_id": "es-MX",
    "country_code_en_us_label_id": "English (United States)",
    "country_code_en_ca_label_id": "English (Canada)",
    "country_code_fr_ca_label_id": "francais (Canada)",
    "country_code_es_mx_label_id": "Espanol (Mexico)",
    "country_code_pl_pl_label_id": "Polish",
    "country_code_zh_cn_label_id": "Chinese",
    "configure_combination_id": "CONFIGURE TOP COMBINATION",
    "equipment_status": "EQUIPMENT STATUS",
    "preventative_maintenance": "PREVENTATIVE MAINTENANCE",
    "service_id": "Service",
    "selection_timeout": "CONFIGURE SELECTION TIMEOUT",
    "configure_selection_timeout": "CONFIGURE CLEAR SELECTION TIMEOUT",
    "timeout_id": "TIMEOUT",
    "increase_timeout": "INCREASE TIMEOUT",
    "decrease_timeout": "DECREASE TIMEOUT",
    "dashboard_id": "DASHBOARD",
    "restart_id": "RESTART",
    "shutdown_id": "SHUTDOWN",
    "valve_offline_id": "Valve Controller Offline",
    "motherboard_offline_id": "Motherboard Controller Offline",
    "motherboard_temp_id": "Motherboard Temperature Out of Range",
    "cpu_temp_id": "CPU Temperature Out of Range",
    "cpu_fan_id": "CPU Fan Speed Out of Range",
    "ssd_temp_id": "SSD Temperature Out of Range",
    "ssd_life_id": "SSD Remaining Life Out of Range",
    "invalid_id": "Invalid Inventory Settings",
    "start_id": "Starting Up...",
    "pouring_id": "Pouring...",
    "preparing_unit_id": "Preparing Unit...",
    "ada_false_id": "ADA Not Present",
    "touch_false_id": "Touch Not Present",
    "door_id": "Door Open",
    "ice_id": "Ice Level Low",
    "ice_box_id": "Ice Box Open",
    "title_id": "ACTIONS",
    "audio_button_id": "VOLUME ADJUSTMENT",
    "configure_customer_banner_button_id": "CONFIGURE CUSTOMER BANNER",
    "define_flow_rates_button_id": "DEFINE FLOW RATES",
    "auto_fill_adjustment_button_id": "AUTO FILL ADJUSTMENT",
    "dashboard_button_id": "DASHBOARD",
    "display_off_button_id": "TURN OFF DISPLAY",
    "exit_to_windows_button_id": "EXIT TO WINDOWS",
    "initial_setup_button_id": "INITIAL SETUP",
    "prime_button_id": "PRIMING",
    "power_button_id": "SYSTEM REBOOT/SHUTDOWN",
    "sanitization_button_id": "SANITIZATION",
    "screen_cleaning_button_id": "SCREEN CLEANING",
    "valve_layout_button_id": "VIEW VALVE LAYOUT",
    "change_language_button_id": "CHANGE SERVICE LANGUAGE",
    "change_consumer_u_i_language_button_id": "CHANGE CONSUMER LANGUAGE",
    "curated_mixology_button_id": "CURATED MIXOLOGY",
    "sensor_pack_button_id": "SENSOR PACK CONFIGURATION",
    "customize_u_i_button_id": "CUSTOMIZE UI",
    "customize_ui_select_a_customization": "SELECT A CUSTOMIZATION FROM THE LIST BELOW",
    "header_id": "VOLUME ADJUSTMENT",
    "message_id": "Adjust volume using the slider or incremental adjust buttons below",
    "close_id": "CLOSE",
    "auto_fill_adjustments_id": "AUTO FILL ADJUSTMENTS",
    "cancel_delete_id": "CANCEL DELETE",
    "confirm_delete_id": "CONFIRM DELETE POUR TIMES",
    "delete_pour_id": "DELETE POUR TIMES",
    "manage_cup_id": "MANAGE{0}CUP{0}SIZES",
    "manage_ice_id": "MANAGE{0}ICE Fill{0}VOLUMES",
    "press_confirm_id": "YOU ARE ABOUT TO DELETE ALL POUR TIMES, PRESS CONFIRM TO DELETE",
    "record_auto_id": "RECORD{0}AUTO FILL{0}POURS",
    "select_presets_id": "SELECT PRESETS TO ADJUST",
    "view_carb_id": "VIEW CARBONATION GROUPINGS",
    "confirm_and_continue_id": "CONFIRM AND CONTINUE BY DEFINING ALL AUTOFILL{0}RECORDINGS",
    "confirm_delete_single_brand_id": "CONFIRM DELETING SINGLE BRAND POUR TIMES FOR {0}",
    "confirm_restore_default_id": "CONFIRM{0}RESTORE DEFAULT",
    "continue_and_confirm_id": "CONTINUE{0}AND CONFIRM",
    "current_carb_group_id": "VALVE # {0} - CURRENT CARBONATION GROUP",
    "define_single_brand_id": "DEFINE SINGLE BRAND",
    "product_removed_id": "THIS PRODUCT HAS BEEN REMOVED FROM ITS ORIGINAL GROUP{0}RETURN {1} TO THE {2} BY PRESSING \\\"RETURN TO DEFAULT\\\"",
    "return_to_default_id": "RETURN TO DEFAULT",
    "warning_message_id": "! {1} HAS THE SAME POUR TIMES AS {2}.{0}TO MODIFY POUR TIMES FOR {1} *ONLY* PRESS \"DEFINE SINGLE BRAND\" !",
    "cleaner_id": "CLEANER",
    "error_id": "Error",
    "done_id": "DONE",
    "cancel_id": "CANCEL",
    "no_valve_mapping_id": "Error: No valve mapping found for location index {0}. Please check Inventory Hardware Mapping Plugin.",
    "halted_id": "Dispensing halted",
    "step1_description_id": "PLACE TUBING IN BUCKET OF WARM WATER AND PRESS CONTINUE BELOW",
    "step1_title_id": "PRE-RINSE",
    "step_s1b_message_id": "RINSE WILL CONTINUE FOR {0} {1}",
    "step1b_header_id": "PURGING",
    "step1b_message_id": "PURGING WILL CONTINUE FOR 2 MINUTES.",
    "step2a_header_id": "PREPARATION",
    "step2a_message_id": "FOLLOW DIRECTIONS BELOW",
    "step_s2a_title_id": "SANITIZE",
    "step_s2a_description_id": "REMOVE CONNECTOR FROM WATER AND ATTACH TO BEVCLEAN BIB AND PRESS CONTINUE BELOW",
    "step2b_header_id": "RINSING/SOAKING",
    "step2b_message_id": "RINSING & SOAKING WILL CONTINUE FOR 10 MINUTES",
    "step_s2b_header_id": "SANITIZING",
    "step_s2b_message_id": "SANITIZING WILL CONTINUE FOR {0} {1}",
    "remove_tubing_id": "REMOVE TUBING FROM WATER AND PRESS CONTINUE BELOW",
    "purge_tubing_id": "PURGE TUBING",
    "follow_id": "FOLLOW DIRECTIONS BELOW",
    "step2_title_id": "RINSE/SOAK",
    "step2_description_id": "PLACE TUBING IN BUCKET OF WARM WATER AND PRESS CONTINUE BELOW",
    "step2c_header_id": "PURGE TUBING",
    "step2c_message_id": "FOLLOW DIRECTIONS BELOW",
    "step2c_description_id": "REMOVE TUBING FROM WATER AND PRESS CONTINUE",
    "step2d_header_id": "PURGING",
    "step2d_message_id": "PURGING WILL CONTINUE FOR 2 MINUTES",
    "step3_description_id": "PLACE TUBING IN PREPARED KAY-5 SOLUTION ACCORDING TO PACKET DIRECTIONS AND PRESS CONTINUE BELOW",
    "step3_title_id": "SANITIZE/SOAK",
    "step3a_header_id": "PREPARATION",
    "step3a_message_id": "FOLLOW DIRECTIONS BELOW",
    "step3a_title_id": "SANITIZE/SOAK",
    "step3a_description_id": "PLACE TUBING IN PREPARED KAY-5 SOLUTION ACCORDING TO PACKET DIRECTIONS AND PRESS CONTINUE BELOW",
    "step3b_header_id": "SANITIZING/SOAKING",
    "step3b_message_id": "SANITIZING & SOAKING WILL CONTINUE FOR 20 MINUTES",
    "step_s3a_header_id": "SOAKING",
    "step_s3a_message_id": "SOAKING WILL CONTINUE FOR {0} {1}",
    "step_s3a_title_id": "SOAK",
    "step_s3a_description_id": "REMOVE CONNECTOR FROM BIB, PLACE TUBING IN CLEAN WATER AND PRESS CONTINUE BELOW",
    "step4_description_id": "PLACE TUBING IN CLEAN WATER AND PRESS CONTINUE BELOW",
    "step4_title_id": "POST-RINSE",
    "step4a_header_id": "PREPARATION",
    "step4a_message_id": "FOLLOW DIRECTIONS BELOW",
    "step4a_title_id": "POST-RINSE",
    "step_s4a_title_id": "POST-RINSE",
    "step_s4a_description_id": "REMOVE CONNECTOR FROM BIB, PLACE TUBING IN CLEAN WATER AND PRESS CONTINUE BELOW",
    "step4a_description_id": "PLACE TUBING IN CLEAN WATER AND PRESS CONTINUE BELOW",
    "step4b_header_id": "RINSING",
    "step4b_message_id": "RINSING WILL CONTINUE FOR {0} {1}",
    "step4c_header_id": "CLEANING COMPLETE",
    "step4c_message_id": "RECONNECT BIB",
    "second_id": "SECOND",
    "seconds_id": "SECONDS",
    "minutes_id": "MINUTES",
    "rinsing_id": "RINSING",
    "ice_door_id": "ICE DOOR IS OPEN.",
    "unlock_id": "UNLOCK DISPENSE",
    "lock_id": "LOCK DISPENSE",
    "confirm_unlock_id": "CONFIRM VALVE UNLOCK",
    "confirm_lock_id": "CONFIRM VALVE LOCK DISPENSE",
    "header_unlock_id": "VALVE # {0} - UNLOCK DISPENSE",
    "header_lock_id": "VALVE # {0} - LOCK DISPENSE",
    "close_button_id": "CLOSE",
    "prime_id": "PRIME",
    "start_dispense_id": "START PRIME DISPENSE",
    "start_timed_id": "START TIMED PRIME",
    "out_of_stock_id": "OUT OF STOCK",
    "empty_id": "BIB is empty. Replace with new product in back room.",
    "ready_id": "VALVE # {0} - CURRENT ASSIGNMENT",
    "not_in_use_id": "UNASSIGNED",
    "change_header_id": "BIB CHANGE",
    "change_message_id": "Follow the steps below to change bib in back room.",
    "clean_header1_id": "PREPARATION",
    "clean_message1_id": "WIPE CLEAN PROBES, FITMENT. PLACE WASTE COLLECTION TRAY BELOW NOZZLE. CONNECT WITH TUBING ADAPTER.",
    "valve_assign_id": "VALVE ASSIGNMENT",
    "change_valve_assign_id": "VALVE # {0} - CHANGE VALVE ASSIGNMENT",
    "change_product_id": "Select a new product for this valve below",
    "prime_valve_id": "VALVE # {0} - PRIME VALVE",
    "stop_dispense_id": "STOP PRIME DISPENSE",
    "priming_id": "PRIMING",
    "timed_priming_id": "TIMED PRIMING",
    "stop_timed_id": "STOP TIMED PRIME",
    "prime_time_id": "\r\n\r\nFixed Prime time is {0} seconds.",
    "brix_calibration_id": "VALVE # {0} - BRIX CALIBRATION",
    "calibrating_id": "CALIBRATING",
    "confirm_unlock_dispense_id": "CONFIRM UNLOCK DISPENSE",
    "locked_id": "LOCKED",
    "confirm_lock_dispense_id": "CONFIRM LOCK DISPENSE",
    "brix_id": "BRIX DISPENSE",
    "replenish_id": "REPLENISH BIB",
    "change_valve_id": "CHANGE VALVE ASSIGNMENT",
    "brix4_id": "4 SECOND BRIX CALIBRATION",
    "sanitization_id": "SANITIZATION",
    "view_layout_id": "VIEW VALVE LAYOUT",
    "save_id": "SAVE & FINSH",
    "auto_fill_id": "AUTO FILL ADJUSTMENT",
    "complete_id": "COMPLETE",
    "select_id": "SELECT",
    "unavailable_id": "UNAVAILABLE",
    "confirm_close_id": "CONFIRM & CLOSE",
    "locked_products_id": "LOCKED PRODUCTS DETECTED{0}REMOVE LOCK TO CONTINUE",
    "record_auto_fill_id": "SET POUR TIMES FOR CARBONATION GROUPS",
    "select_group_id": "SELECT GROUP",
    "header_choose_default_language_id": "Choose Default Language",
    "header_choose_secondary_language_id": "Choose Secondary Language",
    "save_and_select_secondary_language_id": "SAVE & SELECT SECONDARY LANGUAGE (OPTIONAL)",
    "instructions_id": "Selected desired language",
    "ok_id": "OK",
    "large_bib_filter_gallons_id": "FILTER BY{0}5 GALLON BIBS",
    "small_bib_filter_gallons_id": "FILTER BY{0}3 GALLON BIBS",
    "large_bib_filter_liters_id": "FILTER BY{0}20L BIBS",
    "small_bib_filter_liters_id": "FILTER BY{0}12L BIBS",
    "sku_number_id": "SKU NO. {0} {1}",
    "catalog_loading_id": "Please wait while the remaining catalog is loaded...",
    "flavor_shot_filter_button_text_id": "FLAVOR SHOT",
    "syrup_filter_button_text_id": "SYRUP",
    "water_filter_button_text_id": "WATER",
    "loading_id": "Loading",
    "disabled_id": "DISABLED",
    "enabled_id": "ENABLED",
    "touch_a_mix_id": "TOUCH A MIX BELOW TO TOGGLE IT ON THE CONSUMER UI",
    "enable_button_id": "ENABLE",
    "enabled_button_id": "ENABLED",
    "override_id": "SELECT OVERRIDE",
    "override_kfc_uk_id": "Kentucky Fried Chicken - United Kingdom",
    "override_none_id": "Default Configuration",
    "override_subway_canada_id": "Subway Canada",
    "override_subway_us_id": "Subway US",
    "save_button_id": "SAVE",
    "select_attract_loop_id": "Select Attractor Loop",
    "select_button_id": "SELECT",
    "selected_button_id": "SELECTED",
    "age_id": "23",
    "valve_assignment_title_id": "VALVE ASSIGNMENT",
    "actions_title_id": "ACTIONS",
    "system_id": "SYSTEM",
    "display_power_id": "Display Power",
    "turn_off_id": "Do you wish to turn off the display?",
    "confirm_id": "CONFIRM",
    "valve_id": "VALVE CONTROLLER",
    "ada_id": "ADA CONTROLLER",
    "valve_connect_id": "Valve controller connected. Firmware version: ",
    "connected_id": "Connected",
    "device_id": "Device Not Found",
    "hardware_id": "Hardware ID",
    "firmware_id": "Firmware Version",
    "dx3_id": "DX3/LX3",
    "dx3_connect_id": "Connected. Firmware version: ",
    "sen_id": "SEN CONNECTION",
    "modem_id": "MODEM",
    "sensor_pack_id": "SENSOR PACK",
    "model_id": "Model",
    "mtr_api_false_id": "MTR API Not Present on Router IP Address",
    "network_id": "Network",
    "not_connected_id": "Not Connected",
    "not_installed_id": "Not Installed",
    "product_id": "Product Id",
    "radio_id": "Radio Firmware Version",
    "roaming_id": "Roaming",
    "router_ip_id": "Router IP Address",
    "signal_strength_id": "Signal Strength ",
    "updating_id": "Updating SEN connection status...",
    "undi_id": "Unique Identifier: {0}\r\n\r\n",
    "undi_false_id": "Unique Identifier: Not Present\r\n\r\n",
    "kiosk_id": "KioskID: {0}\r\n\r\n",
    "kiosk_false_id": "KioskID: Not Present\r\n\r\n",
    "apriva_id": "Apriva Server: {0}",
    "service_false_id": "{0}: Not installed!{1}",
    "running_id": "Running",
    "stopped_id": "Stopped",
    "mac_id": "Mac Address",
    "ip_id": "IP Address",
    "offline_id": "OFFLINE",
    "online_id": "ONLINE",
    "apriva_talk_id": "AprivaTalk Socket Server",
    "watchdog_id": "Watchdog Service",
    "not_present_id": "Not Present",
    "sen_id_id": "SEN ID: {0}{1}",
    "sen_id_false_id": "SEN ID: Not Present{0}",
    "sen_scheduler_id": "SEN Scheduler",
    "sen_talk_id": "SEN Talk",
    "version_id": "Version: {0}{1}",
    "fan_low_id": "CPU Fan Speed Is Too Low\r\n\r\n",
    "cpu_temp_high_id": "CPU Temperature Is Too High\r\n\r\n",
    "system_temp_high_id": "System Temperature Is Too High\r\n\r\n",
    "ssd_temp_high_id": "SSD Temperature Is Too High\r\n\r\n",
    "ssd_temp_false_id": "SSD Temperature Is Invalid\r\n\r\n",
    "ssd_life_low_id": "SSD Remaining Life Is Too Low\r\n\r\n",
    "ssd_life_false_id": "SSD Remaining Life Is Invalid\r\n\r\n",
    "system_temp_id": "System Temperature is {0}{1} C\r\n",
    "fan_id": "CPU Fan Speed is {0} RPM\r\n",
    "ssd_power_id": "SSD Total Power On Hours is {0}\r\n",
    "ssd_shutdown_id": "SSD Unsafe Shutdown Count is {0}\r\n",
    "not_found_id": "Not Found",
    "nuc_serial_number_id": "NUC Serial Number is {0}",
    "oz_per_sec_id": "oz/s",
    "ml_unit_id": "ml",
    "keypad_subtitle_id": "ENTER MILLILITERS POURED DURING BRIX 4 SECOND DISPENSE",
    "define_id": "DEFINE FLOW RATES",
    "enter_pin": "ENTER PIN",
    "high_still_id": "HIGH STILL",
    "low_still_id": "LOW STILL",
    "high_carb_id": "HIGH CARB",
    "low_carb_id": "LOW CARB",
    "syrup_id": "SYRUP",
    "flavor_id": "FLAVOR SHOT",
    "carb_rate_id": "CARB WATER FLOW RATE",
    "low_carb_rate_id": "LOW CARB WATER FLOW RATE",
    "water_rate_id": "WATER FLOW RATE",
    "low_water_rate_id": "LOW WATER FLOW RATE",
    "syrup_rate_id": "SYRUP FLOW RATE",
    "flavor_rate_id": "FLAVOR SHOT FLOW RATE",
    "true_id": "TRUE",
    "false_id": "FALSE",
    "yes_id": "Yes",
    "no_id": "No",
    "ice_box_closed_id": "Ice Box Closed",
    "ice_box_not_found_id": "Ice Box Not Found",
    "ice_box_open_id": "Ice Box Open",
    "ice_box_status_id": "ICE BOX STATUS",
    "access_level_id": "ACCESS LEVEL: {0}",
    "tower_version_id": "SPIRE: {0}",
    "kiosk_frame_version_id": "KIOSKFRAME: {0}",
    "image_version_id": "DISK IMAGE: {0}",
    "bios_version_id": "BIOS: {0} - {1}",
    "unit_type_id": "Platform",
    "exit_button_id": "EXIT TO CONSUMER UI",
    "default_id": "DEFAULT",
    "instructions_cups_id": "1) SELECT THE CUPS AVAILABLE AT THE SITE{0}2) PRESS \\\"DEFAULT\\\" TO SELECT THE MOST COMMONLY USED CUP",
    "instructions_ice_id": "1) SELECT THE ICE LEVELS AVAILABLE AT THE SITE{0}2) PRESS \\\"DEFAULT\\\" TO SELECT THE MOST COMMONLY USED ICE LEVEL",
    "manage_cup_sizes_id": "MANAGE CUP SIZES",
    "manage_ice_volumes_id": "MANAGE ICE FILL VOLUMES",
    "set_default_id": "SET DEFAULT",
    "unassigned_id": "UNASSIGNED",
    "unassigned_lower_id": "Unassigned",
    "confirm_reboot_id": "CONFIRM REBOOT",
    "confirm_suspend_id": "CONFIRM SUSPEND",
    "confirm_shutdown_id": "CONFIRM SHUTDOWN",
    "confirm_exit_id": "CONFIRM EXIT",
    "hint_reboot_id": "This selection will close the Kiosk software, reboot its internal PC and launch the Kiosk software.",
    "hint_suspend_id": "This selection will put the Kiosk's internal PC in sleep mode.",
    "hint_shutdown_id": "This selection will close the Kiosk software and shutdown its internal PC.",
    "hint_exit_id": "This selection will close the Kiosk software and return to Windows.",
    "power_down_exit_id": "POWER DOWN AND EXIT",
    "select_confirm_id": "SELECT DESIRED ACTION, THEN CONFIRM",
    "first_reboot_id": "FIRST START UP COMPLETION REBOOT",
    "edit_reboot_id": "EDIT START UP SETTINGS REBOOT",
    "reboot_confirm_id": "REBOOT CONFIRM",
    "suspend_confirm_id": "SUSPEND CONFIRM",
    "shutdown_confirm_id": "SHUT DOWN CONFIRM",
    "exit_confirm_id": "EXIT TO WINDOWS CONFIRM",
    "reboot_id": "REBOOT",
    "suspend_id": "SUSPEND",
    "exit_id": "EXIT TO WINDOWS",
    "water_filter_id": "Water Filter Is OK\r\nDate Of Last Change:      {0}\r\nDate Of Next Change:     {1} ",
    "preventative_id": "PREVENTATIVE MAINTENANCE",
    "water_filter_reminder_id": "WATER FILTER REMINDER",
    "sanitation_id": "LINES & VALVES SANITATION",
    "power_id": "POWER SUPPLY FAN CLEAN",
    "nuc_id": "NUC FAN CLEAN",
    "reset_id": "RESET",
    "water_id": "WATER FILTER",
    "needs_service_id": "Water Filter Needs Service\r\nDate Of Last Change:      {0}\r\nDate Of Next Change:     {1} ",
    "lines_valves_id": "Lines and Valves Are OK",
    "power_fan_id": "Power Supply Fan Is OK",
    "nuc_fan_id": "NUC Fan Is OK",
    "brix_pour_button_id": "Brix 4 Second Pour",
    "select_valves_id": "SELECT VALVES ({0} MAXIMUM) TO TEST",
    "stop_id": "STOP",
    "clear_id": "Clear",
    "big_brix_button_id": "BRIX DISPENSE",
    "touch_offline_id": "Touch Controller is Offline.",
    "auto_fill_recorded_id": "AN AUTO FILL WAS RECORDED{0}{0}TEST, RE-RECORD OR SAVE AUTO FILL",
    "child_id": "Child",
    "confirm_selected_id": "! CONFIRM SELECTED CUP SIZE AND ICE VOLUME ARE POSITIONED UNDER NOZZLE BEFORE RECORDING !",
    "full_id": "Full",
    "half_id": "Half",
    "ice_door_open_id": "ICE DOOR OPEN",
    "invalid_pour_time_id": "INVALID POUR TIME",
    "large_id": "Large",
    "medium_id": "Medium",
    "none_id": "None",
    "no_product_id": "NO PRODUCT TO POUR{0}VALVES MAY BE LOCKED",
    "pitcher_id": "Pitcher",
    "press_and_hold_id": "PRESS AND HOLD THIS BUTTON TO RECORD",
    "record_auto_fill_pour_id": "RECORD AUTO FILL POUR",
    "recording_id": "RECORDING...",
    "recording_apply_id": "RECORDING AUTO FILL WILL APPLY TO",
    "recording_will_apply_id": "! RECORDING AUTO FILL WILL APPLY TO AL BRANDS IN GROUP !",
    "release_button_id": "RELEASE BUTTON TO STOP",
    "re_record_id": "RE-RECORD AUTO FILL",
    "save_auto_fill_id": "SAVE AUTO FILL",
    "select_cup_size_id": "SELECT CUP SIZE FOR AUTO FILLS TO BE RECORDED",
    "select_ice_volumes_id": "SELECT ICE VOLUME FOR AUTO FILL TO BE RECORDED",
    "test_recording_id": "TEST RECORDING",
    "x_large_id": "X-Large",
    "continue_id": "CONTINUE",
    "sanitize_id": "SANITIZATION",
    "ice_open_id": "Ice Box is Open.  No cleaning is possible.",
    "prepare_id": "PREPARATION",
    "clean_id": "CLEANER",
    "screen_close_id": "SCREEN WILL CLOSE IN {0} SECONDS\r\nREMEMBER TO DRY SCREEN",
    "initial_setup_title_id": "{0} FIRST TIME SETUP",
    "edit_setup_title_id": "EDIT {0} FIRST TIME SETUP",
    "health_monitor_offline_id": "\r\nHEALTH MONITOR IS OFFLINE. MACHINE STATUS CAN NOT BE DETERMINED AT THIS TIME.",
    "sen_services_id": "SEN Services\r\n",
    "sen_services_stopping_id": "\r\nPlease wait while SEN services are stopped.",
    "sen_services_stopped_id": "SEN services stopped successfully, continue with initial setup.",
    "sen_services_already_stopped_id": "SEN services already stopped.",
    "unit_location_id": "Unit Location",
    "unit_location_instructions_id": "Select the location where the unit will be deployed",
    "unit_type_instructions_id": "The configuration type for this unit",
    "machine_status_id": "Machine Status\r\n",
    "machine_status_instructions_id": "Check subsystems status and select the appropriate action.",
    "kiosk_name_setup_id": "Kiosk Name Setup\r\n",
    "kiosk_name_setup_instructions_id": "\r\nAssign the Kiosk Name for this Spire installation.",
    "kiosk_setup_id": "Kiosk ID Setup\r\n",
    "kiosk_setup_instructions_id": "\r\nAssign the Kiosk ID for this Spire installation.",
    "sen_setup_id": "SEN Setup\r\n",
    "sen_setup_instructions_id": "\r\nAssign the UNDI and then select the SEN database type.",
    "setup_summary_id": "Spire Setup Summary\r\n",
    "setup_summary_instructions_id": "\r\nReview the item values below. If the choices are acceptable then click the button for each item.\r\n\r\nIf an item value is not acceptable select the appropriate action.\r\n\r\nIf all item values are accepted after clicking Finished a reboot is required.",
    "sen_database_id": "SEN Database",
    "sen_database_type_id": "SEN Database Type",
    "environment_development_id": "Development",
    "environment_fit_id": "FIT",
    "environment_production_id": "Production",
    "valve_controller_ok_id": "Valve Controller OK",
    "system_inventory_ok_id": "System Inventory OK",
    "mb_controller_ok_id": "MB Controller",
    "kiosk_name_id": "Kiosk Name",
    "spire_id": "SPIRE",
    "spire20_id": "SPIRE 2.0",
    "spire20_crew_id": "SPIRE 2.0 CREW",
    "spire30_id": "SPIRE 3.0",
    "spire31_id": "SPIRE 3.1",
    "spire41_id": "SPIRE 4.1",
    "spire50_id": "SPIRE 5.0",
    "drive_thru_id": "DRIVE THRU",
    "us_id": "US",
    "canada_id": "CANADA",
    "back_button_id": "BACK",
    "cancel_button_id": "CANCEL",
    "continue_button_id": "CONTINUE",
    "finish_button_id": "FINISHED",
    "cancel_text_id": "Cancel",
    "summary_kiosk_name_id": "Kiosk Name",
    "summary_kiosk_id": "Kiosk ID",
    "summary_sen_database_type_id": "SEN Database Type",
    "summary_undi_id": "UNDI",
    "modem_connection_error_id": "Modem connection error\r\n\r\n",
    "modem_power_id": "Modem Power",
    "modem_ethernet_id": "Ethernet Connected",
    "modem_carrier_detection_id": "CD (Carrier Detection)",
    "registration_status_title_id": " REGISTRATION STATUS\r\n      \r\n    ",
    "modem_connectivity_title_id": " CHECKING CONNECTION",
    "modem_connectivity_error_id": "MODEM CONNECTIVITY ERROR",
    "modem_power_troubleshooting_id": "Please check that the modem is powered on and that the Ethernet cable is properly connected between the modem and the NUC PC",
    "modem_ethernet_troubleshooting_id": "Please check that the Ethernet cable is properly connected between the modem and the NUC PC",
    "modem_other_troubleshooting_id": "Please check the modem antenna installation",
    "registration_error_title_id": " REGISTRATION ERROR\r\n      ",
    "registration_error_description_id": "Registration is unable to complete. Please log issue into CETS\r\n      \r\n    ",
    "registration_review_title_id": " REGISTRATION REVIEW",
    "registration_review_description_id": "Registration completed",
    "registration_cannot_complete_id": "Registration is unable to complete. Please review log.",
    "call_sen_support_id": "Please call SEN Support",
    "sen_registration_unable_to_complete_id": ": System Error\\nRegistration is unable to complete",
    "retry_id": "RETRY",
    "start_registration_button_id": "START REGISTRATION",
    "registration_id": "Registration Id",
    "motherboard_controller_status_label_id": "MB Controller",
    "system_inventory_status_label_id": "System Inventory OK",
    "valve_controller_status_label_id": "Valve Controller",
    "ada_controller_status_label_id": "ADA Controller",
    "dx3_controller_status_label_id": "DX3/LX3 Controller",
    "international_id": "International",
    "left_id": "Left Bank",
    "right_id": "Right Bank",
    "bank1_id": "Bank 1",
    "bank2_id": "Bank 2",
    "unknown_id": "UNKNOWN",
    "flavor_shot_id": "FLAVORSHOT",
    "selected_id": "SELECTED",
    "finish_id": "FINISH",
    "system_status_id": "SYSTEM STATUS",
    "view_layout_title_id": "VIEW LAYOUT & ASSIGNMENT",
    "prime_popup_title": "SELECT VALVES (5 MAXIMUM) TO TEST",
    "start_prime_id": "START",
    "clear_prime_id": "CLEAR",
    "brix_pour_id": "BRIX 4 SECOND POUR",
    "start_prime_dispense_id": "START PRIME DISPENSE",
    "start_timed_prime_id": "START TIMED PRIME",
    "valve_prime_id": "VALVE # {0} - Prime Valve",
    "brix_dispense_button_id": "BRIX DISPENSE",
    "bib_change_instructions": "Follow the steps below to change the bib in back room.",
    "bib_change": "BIB CHANGE",
    "next_button_id": "NEXT",
    "previous_button_id": "PREVIOUS",
    "prime_vavle_button_id": "PRIME",
    "touch_controller_button_id": "TOUCH CONTROLLER",
    "flow_rate_configure": "Select a Rate to Configure.",
    "flow_rate_message": "Number must be between 0.01 and 1000",
    "log_viewer_id": "LOG VIEWER",
    "configure_legacy_valves": "CONFIGURE LEGACY VALVES",
    "select_brand_id": "SELECT BRAND",
    "sen_connectivity_id": "SEN CONNECTIVITY",
    "sen_equipment_set_up_id": "SEN EQUIPMENT SET UP",
    "sen_diagnostics_id": "SEN SET UP & DIAGNOSTICS",
    "enter_serial_number_id": "Enter Serial Number",
    "equipment_serial_number_id": "Equipment Serial Number",
    "retry_maximum_reached_id": "Retry Maximum Reached",
    "sen_id_title": "SEN Id: ",
    "refresh_id": "REFRESH",
    "purge_data_u_i_language_button_id": "PURGE DATA",
    "purge_data_instructions_id": "Press the button to delete all SEN data on the system. Insert a USB to save a backup.",
    "purge_data_id": "Purge Data",
    "purge_and_backup_data_id": "Backup & Purge Data",
    "purge_data_file_size": "File Size",
    "purge_data_space_remaining": "Space Remaining",
    "purge_data_usb_ready": "USB Ready",
    "purge_data_usb_not_enough_free_space": "USB detected, but not enough free space available for backup.",
    "purge_data_usb_size_out_of_range": "USB detected, but not within allowed total size range (too large or too small). 8 GB minimum needed.",
    "purge_data_usb_not_detected": "No USB Detected",
    "purge_data_confirm": "Are you sure?",
    "purge_data_purge_complete": "Purge Complete",
    "purge_data_purge_and_backup_complete": "Backup & Purge Complete",
    "kiosk_id_setup_id": "Kiosk ID Setup",
    "kiosk_id_setup_instructions_id": "Assign the Kiosk ID for this Spire installation.",
    "kiosk_id_id": "Kiosk ID",
    "summary_kiosk_id_id": "Kiosk ID",
    "sen_web_service_failure_id": "101: Failed to invoke the SEN Registration Web Service Registration is unable to complete",
    "retry_button_id": "REFRESH",
    "nutrition_facts_button_id": "NUTRITION FACTS",
    "nutrition_facts_title_id": "Nutrition Facts",
    "auto_activation_email_button_id": "Show Email Details",
    "auto_activation_message_id": "Activation is complete, but the unit is NOT connected. Ensure an email was sent with required details.",
    "auto_activation_sub_title_id": "Activation Complete",
    "auto_activation_title_id": "Auto Activation",
    "pbc_no_connection_addr_id": "Customer Address",
    "pbc_no_connection_addr1_id": "Address Line 1",
    "pbc_no_connection_addr2_id": "Address Line 2",
    "pbc_no_connection_asset_num_id": "Spire Asset Number",
    "pbc_no_connection_city_id": "City",
    "pbc_no_connection_cof_id": "Customer number (COF)",
    "pbc_no_connection_cust_name_id": "Customer Name",
    "pbc_no_connection_equip_loc_id": "Equipment Location",
    "pbc_no_connection_spire_sn_id": "Spire Unit Serial Number",
    "pbc_no_connection_state_id": "State / Province / Region",
    "pbc_no_connection_sub_title_id": "Enter the required information",
    "pbc_no_connection_title_id": "PBC No connection detected",
    "pbc_no_connection_zip_id": "Zip / Postal Code",
    "reg_error_directions_id": "Directions on how to proceed",
    "reg_error_sub_title_id": "No connection detected. Follow the Diagnostics below",
    "reg_error_title_id": "CONNECTIVITY ERROR",
    "asset_edit_not_found_id": "Spire Asset Number <#> is not found.",
    "asset_edit_required_info_id": "Enter the required information",
    "correct_id": "Correct",
    "email_action_required_id": "ACTION REQUIRED",
    "email_bottler_id": "Bottling Partner",
    "email_bottler_id_id": "Bottler Customer ID",
    "email_cof_id": "Customer Number (COF)",
    "email_country_id": "Country",
    "email_cust_name_id": "Customer Name",
    "email_take_a_picture_id": "Take a picture of the following box and send to email",
    "email_asset_id": "Spire Asset Number",
    "equip_cust_address_id": "Customer Address",
    "email_cust_address_id": "Customer Address",
    "equip_disk_img_id": "Disk Image",
    "email_disk_img_id": "Disk Image",
    "equip_location_id": "Equipment Location",
    "email_location_id": "Equipment Location",
    "equip_modem_id": "Modem Serial Number",
    "email_modem_id": "Modem Serial Number",
    "equip_nuc_id": "NUC Serial Number",
    "email_nuc_id": "NUC Serial Number",
    "equip_sen_id": "SEN Diag",
    "equip_sen_diagnostic_summary_id": "SEN Diagnostics Summary",
    "email_sen_diagnostics_summary_id": "SEN Diagnostics Summary",
    "equip_setup_ast_id": "Atlantic Standard Time",
    "equip_setup_bottling_partner_id": "Which Bottling Partner are you from?",
    "equip_setup_cst_id": "Central Standard Time",
    "equip_setup_est_id": "Eastern Standard Time",
    "equip_setup_mst_id": "Mountaint Standard Time",
    "equip_setup_nst_id": "Newfoundland Standard Time",
    "equip_setup_pst_id": "Pacific Standard Time",
    "equip_setup_spire_country_id": "What Country are you in?",
    "equip_setup_spire_type_id": "What Spire Unit Type is this?",
    "equip_setup_time_zone_id": "Time Zone",
    "email_time_zone_id": "Time Zone",
    "equip_sn_id": "Spire Unit Serial Number",
    "email_sn_id": "Spire Unit Serial Number",
    "not_correct_id": "Not Correct",
    "validate_message_id": "Validate the Spire Unit Serial Number",
    "validate_sn_example_id": "0000-0000-0000-0000",
    "validate_subtitle_id": "PBC- connection",
    "edit_button_id": "EDIT",
    "auto_activation_complete_id": "Activation complete and the unit is connected!",
    "serial_number_not_found_id": "Spire Unit Serial Number <serial#> and Spire Asset number <asset#> were not found.",
    "equipment_setup_sub_title_id": "Equipment Setup",
    "pbc_connection_sub_title_id": "PBC - connection",
    "equipment_setup_spire_type_id": "What Spire Unit Type is this?",
    "equipment_setup_wait_id": "Please wait...",
    "equipment_setup_what_country_id": "What Country are you in?",
    "equipment_setup_which_bottling_id": "Which Bottling Partner are you from?",
    "time_zone_id": "Time Zone",
    "ib_intl_title_id": "IB/International",
    "email_detail_exceptions_id": "If there are any special exceptions to why this unit is not connected, please note in email (example: unit in basement, no cellular signal)",
    "email_details_id": "Email Details",
    "email_details_readable_id": "Warning: ensure information in box is centered and readable!",
    "other_option_title_id": "OTHER",
    "reg_error_sub_title_dll_error_id": "No connection detected.",
    "required_field_id": "Required",
    "add_cup_button_id": "Add Cup",
    "add_cup_error_id": "Cannot add more than 5 cups",
    "cup_name_header_id": "Cup Name",
    "cup_name_instructions_id": "Enter Name of Cup Below",
    "cup_volume_header_id": "Cup Volume",
    "cup_volume_instructions_id": "Enter Volume of Cup Below",
    "delete_cup_button_id": "Delete Selected Cups",
    "disabled_footer_id": "DISABLED",
    "enabled_footer_id": "ENABLED",
    "fl_oz_id": "Fl Oz",
    "select_cups_id": "SELECT CUPS BELOW TO DELETE",
    "selected_footer_id": "SELECTED",
    "toggle_button_id": "Toggle Calorie Count",
    "calories_id": "${calorie}",
    "unselected_footer_id": "UNSELECTED",
    "title_calorie_count_id": "Calorie Count",
    "button_calorie_count_id": "CALORIE COUNT",
    "bibItem_type_title_id": "SELECT FOR BIB ITEM TYPE",
    "overrides_id": "Overrides",
    "attract_loops_id": "Attract Loops",
    "select_curated_mix_id": "Select Curated Mix",
    "sensor_pack_configuration_button_id": "SENSOR PACK CONFIGURATION",
    "status_title_id": "STATUS",
    "calorie_units_id": "MAINTAIN VOLUME UNITS IN:"
  }
}